alff/__init__.py
alff/_version.py
alff/base.py
alff/cli.py
alff/al/__init__.py
alff/al/active_learning.py
alff/al/finetune.py
alff/al/libal_md_ase.py
alff/al/libal_md_lammps.py
alff/al/schema_active_learn.yml
alff/al/schema_finetune.yml
alff/al/utilal.py
alff/al/utilal_uncertainty.py
alff/al/mlp/mlp_mace.py
alff/al/mlp/mlp_sevenn.py
alff/al/mlp/util_mlp.py
alff/elastic/__init__.py
alff/elastic/elastic.py
alff/elastic/lib_elastic.py
alff/elastic/lib_elate.py
alff/elastic/libelastic_lammps.py
alff/elastic/sampleConfig_elastic.yml
alff/elastic/schema_elastic.yml
alff/elastic/utilelastic.py
alff/gdata/__init__.py
alff/gdata/convert_mpchgnet_to_xyz.py
alff/gdata/gendata.py
alff/gdata/libgen_gpaw.py
alff/gdata/schema_gendata.yml
alff/gdata/util_dataset.py
alff/pes/__init__.py
alff/pes/libpes_gpaw.py
alff/pes/libpes_lammps.py
alff/pes/pes_scan.py
alff/pes/schema_pes_scan.yml
alff/pes/utilpes.py
alff/phonon/__init__.py
alff/phonon/libpho_gpaw.py
alff/phonon/libpho_lammps.py
alff/phonon/phonon.py
alff/phonon/schema_phonon.yml
alff/phonon/utilpho.py
alff/phonon/ref/phonon_ref_code.py
alff/util/__init__.py
alff/util/ase_tool.py
alff/util/tool.py
alff/util/script_ase/__init__.py
alff/util/script_ase/cli_ase_md.py
alff/util/script_ase/cli_gpaw_aimd.py
alff/util/script_ase/cli_gpaw_optimize.py
alff/util/script_ase/cli_gpaw_singlepoint.py
alff/util/script_ase/schema_ase_build.yml
alff/util/script_ase/schema_ase_run.yml
alff/util/script_lammps/__init__.py
alff/util/script_lammps/lammps_code_creator.py
alff/util/script_lammps/schema_lammps.yml
alff/validate/__init__.py
alff-25.12.1.dev4.dist-info/METADATA
alff-25.12.1.dev4.dist-info/WHEEL
alff-25.12.1.dev4.dist-info/entry_points.txt
alff-25.12.1.dev4.dist-info/licenses/LICENSE.md
alff-25.12.1.dev4.dist-info/RECORD
